magql_sqlalchemy/__init__.py
magql_sqlalchemy/check_delete.py
magql_sqlalchemy/filters.py
magql_sqlalchemy/group.py
magql_sqlalchemy/manager.py
magql_sqlalchemy/pagination.py
magql_sqlalchemy/py.typed
magql_sqlalchemy/resolvers.py
magql_sqlalchemy/search.py
magql_sqlalchemy/validators.py
magql_sqlalchemy-1.1.0.dist-info/LICENSE.txt
magql_sqlalchemy-1.1.0.dist-info/WHEEL
magql_sqlalchemy-1.1.0.dist-info/METADATA
magql_sqlalchemy-1.1.0.dist-info/RECORD
