Metadata-Version: 2.1
Name: magql-sqlalchemy
Version: 1.1.0
Summary: Generate a Magql GraphQL API from SQLAlchemy models.
Author: David Lord
Requires-Python: >=3.10
Requires-Dist: magql>=1.0.1
Requires-Dist: sqlalchemy>=2
Project-URL: Changes, https://magql-sqlalchemy.autoinvent.dev/page/changes/
Project-URL: Documentation, https://magql-sqlalchemy.autoinvent.dev
Project-URL: Source, https://github.com/autoinvent/magql-sqlalchemy/
